MANIFEST.in
setup.cfg
setup.py
lava_scheduler.egg-info/PKG-INFO
lava_scheduler.egg-info/SOURCES.txt
lava_scheduler.egg-info/dependency_links.txt
lava_scheduler.egg-info/entry_points.txt
lava_scheduler.egg-info/not-zip-safe
lava_scheduler.egg-info/requires.txt
lava_scheduler.egg-info/top_level.txt
lava_scheduler_app/__init__.py
lava_scheduler_app/admin.py
lava_scheduler_app/api.py
lava_scheduler_app/extension.py
lava_scheduler_app/logfile_helper.py
lava_scheduler_app/models.py
lava_scheduler_app/tests.py
lava_scheduler_app/urls.py
lava_scheduler_app/views.py
lava_scheduler_app/management/__init__.py
lava_scheduler_app/management/commands/__init__.py
lava_scheduler_app/management/commands/scheduler.py
lava_scheduler_app/management/commands/schedulermonitor.py
lava_scheduler_app/management/commands/testjobmigrate.py
lava_scheduler_app/migrations/0001_initial.py
lava_scheduler_app/migrations/0002_auto__chg_field_testjob_device_type.py
lava_scheduler_app/migrations/0003_auto__add_field_testjob_requested_device__add_field_testjob_requested_.py
lava_scheduler_app/migrations/0004_fill_out_device_fields.py
lava_scheduler_app/migrations/0005_auto__del_field_testjob_device_type__del_field_testjob_target.py
lava_scheduler_app/migrations/0006_auto__add_field_testjob_log_file.py
lava_scheduler_app/migrations/0007_merged_migration.py
lava_scheduler_app/migrations/0008_auto__add_field_testjob_results_link.py
lava_scheduler_app/migrations/0009_auto__add_field_testjob_description.py
lava_scheduler_app/migrations/0010_auto__chg_field_testjob_description.py
lava_scheduler_app/migrations/0011_auto__add_tag.py
lava_scheduler_app/migrations/0012_auto__add_field_testjob_submit_token.py
lava_scheduler_app/migrations/0013_auto__add_devicestatetransition.py
lava_scheduler_app/migrations/0014_auto__add_field_device_health_status__add_field_device_last_health_rep.py
lava_scheduler_app/migrations/0015_auto__add_field_testjob_health_check.py
lava_scheduler_app/migrations/0016_auto__add_field_devicetype_health_check_job.py
lava_scheduler_app/migrations/0017_add_lava_health_user.py
lava_scheduler_app/migrations/0018_auto__add_field_testjob_user__add_field_testjob_group__add_field_testj.py
lava_scheduler_app/migrations/0019_set_testjob_owner.py
