Metadata-Version: 1.0
Name: lava-scheduler
Version: 0.28
Summary: LAVA Scheduler Application
Home-page: UNKNOWN
Author: Michael Hudson-Doyle
Author-email: michael.hudson@linaro.org
License: AGPL
Platform: UNKNOWN
